icat/__init__.py
icat/_version.py
icat/models.py
icat/simulate.py
icat/utils.py
icat_sc-0.1.4.dist-info/LICENSE
icat_sc-0.1.4.dist-info/METADATA
icat_sc-0.1.4.dist-info/WHEEL
icat_sc-0.1.4.dist-info/top_level.txt
icat_sc-0.1.4.dist-info/RECORD
