Metadata-Version: 2.1
Name: icat-sc
Version: 0.1.4
Summary: Identify cell states across treatments in single-cell RNA sequencing experiments
Home-page: https://github.com/BradhamLab/icat
Author: Dakota Y. Hawkins
Author-email: dyh0110@bu.edu
License: BSD
License-File: LICENSE
Requires-Dist: apricot-select
Requires-Dist: igraph
Requires-Dist: ncfs
Requires-Dist: numpy
Requires-Dist: pandas
Requires-Dist: scanpy
Requires-Dist: scikit-learn
Requires-Dist: scipy
Requires-Dist: louvain
Requires-Dist: sslouvain
